xnat_access/__init__.py
xnat_access/upload.py
xnat_access/version.py
xnat_access-0.6.dist-info/entry_points.txt
xnat_access-0.6.dist-info/LICENSE
xnat_access-0.6.dist-info/WHEEL
xnat_access-0.6.dist-info/METADATA
xnat_access-0.6.dist-info/RECORD
